MANIFEST.in
README.txt
setup.py
docs/HISTORY.txt
docs/INSTALL.txt
docs/LICENSE.GPL
docs/LICENSE.txt
quintagroup/__init__.py
quintagroup.theme.whiteblack.egg-info/PKG-INFO
quintagroup.theme.whiteblack.egg-info/SOURCES.txt
quintagroup.theme.whiteblack.egg-info/dependency_links.txt
quintagroup.theme.whiteblack.egg-info/entry_points.txt
quintagroup.theme.whiteblack.egg-info/namespace_packages.txt
quintagroup.theme.whiteblack.egg-info/not-zip-safe
quintagroup.theme.whiteblack.egg-info/requires.txt
quintagroup.theme.whiteblack.egg-info/top_level.txt
quintagroup/theme/__init__.py
quintagroup/theme/whiteblack/README.txt
quintagroup/theme/whiteblack/__init__.py
quintagroup/theme/whiteblack/configure.zcml
quintagroup/theme/whiteblack/profiles/default/metadata.xml
quintagroup/theme/whiteblack/profiles/default/theme.xml
quintagroup/theme/whiteblack/profiles/default/tinymce.xml
quintagroup/theme/whiteblack/static/favicon.ico
quintagroup/theme/whiteblack/static/index.html
quintagroup/theme/whiteblack/static/manifest.cfg
quintagroup/theme/whiteblack/static/rules.xml
quintagroup/theme/whiteblack/static/tune.xml
quintagroup/theme/whiteblack/static/css/ie8fixes.css
quintagroup/theme/whiteblack/static/css/iefixes.css
quintagroup/theme/whiteblack/static/css/whiteblack.css
quintagroup/theme/whiteblack/static/images/album.png
quintagroup/theme/whiteblack/static/images/bg_globalnav.gif
quintagroup/theme/whiteblack/static/images/bg_globalnav_selected.gif
quintagroup/theme/whiteblack/static/images/bg_top.jpg
quintagroup/theme/whiteblack/static/images/bullet.gif
quintagroup/theme/whiteblack/static/images/icons-sprite.png
quintagroup/theme/whiteblack/static/images/logo.jpg
quintagroup/theme/whiteblack/static/images/pb_close.png
quintagroup/theme/whiteblack/static/images/portlet_top.gif