Metadata-Version: 1.0
Name: quintagroup.theme.whiteblack
Version: 6.0.3
Summary: Free Diazo Theme for Plone 4.1
Home-page: http://skins.quintagroup.com/whiteblack
Author: Quintagroup
Author-email: skins@quintagroup.com
License: GPL
Keywords: web zope plone diazo theme quintagroup
Platform: UNKNOWN
Classifier: Framework :: Plone
Classifier: Intended Audience :: Developers
Classifier: Topic :: Software Development :: Libraries :: Python Modules
Classifier: License :: OSI Approved :: GNU General Public License (GPL)
